flametrack/__init__.py
flametrack/config.ini
flametrack/main.py
flametrack/analysis/__init__.py
flametrack/analysis/config.ini
flametrack/analysis/data_types.py
flametrack/analysis/dataset_handler.py
flametrack/analysis/edge_worker.py
flametrack/analysis/flamespread.py
flametrack/analysis/ir_analysis.py
flametrack/analysis/user_config.py
flametrack/gui/__init__.py
flametrack/gui/draggable_point.py
flametrack/gui/edge_preview_canvas.py
flametrack/gui/edgeresult_canvas.py
flametrack/gui/form.ui
flametrack/gui/imshow_canvas.py
flametrack/gui/main_window.py
flametrack/gui/plotting_utils.py
flametrack/gui/selectable_imshow_canvas.py
flametrack/gui/ui_form.py
flametrack/processing/__init__.py
flametrack/processing/dewarping.py
flametrack/utils/__init__.py
flametrack/utils/math_utils.py
flametrack-1.0.0.dist-info/licenses/LICENSE
flametrack-1.0.0.dist-info/METADATA
flametrack-1.0.0.dist-info/WHEEL
flametrack-1.0.0.dist-info/entry_points.txt
flametrack-1.0.0.dist-info/top_level.txt
flametrack-1.0.0.dist-info/RECORD
