Metadata-Version: 2.4
Name: FlameTrack
Version: 1.0.0
Summary: Python tool for image dewarping and flame front tracking in experimental fire research.
Author: Minh Tam Würzburger, Marc Fehr
Maintainer-email: Marc Fehr <mfehr@uni-wuppertal.de>
License:                                  Apache License
Project-URL: Repository, https://github.com/FireDynamics/FlameTrack
Keywords: fire dynamics,flame tracking,image analysis,computer vision
Classifier: Programming Language :: Python :: 3
Classifier: Operating System :: OS Independent
Requires-Python: <3.14,>=3.10
License-File: LICENSE
Requires-Dist: numpy
Requires-Dist: matplotlib
Requires-Dist: PySide6<=6.9.0
Requires-Dist: pyqtgraph
Requires-Dist: opencv-python
Requires-Dist: progressbar2
Requires-Dist: scipy
Requires-Dist: h5py
Requires-Dist: plotly
Provides-Extra: dev
Requires-Dist: pytest; extra == "dev"
Requires-Dist: pytest-cov; extra == "dev"
Requires-Dist: pytest-qt; extra == "dev"
Requires-Dist: pylint; extra == "dev"
Requires-Dist: pylint-venv; extra == "dev"
Requires-Dist: black; extra == "dev"
Requires-Dist: isort; extra == "dev"
Requires-Dist: mypy; extra == "dev"
Requires-Dist: scikit-image; extra == "dev"
Requires-Dist: coverage[toml]; extra == "dev"
Requires-Dist: sphinx; extra == "dev"
Requires-Dist: sphinx-rtd-theme; extra == "dev"
Requires-Dist: tomli; python_version < "3.11" and extra == "dev"
Requires-Dist: pre-commit; extra == "dev"
Requires-Dist: setuptools-scm; extra == "dev"
Dynamic: license-file
